Azure/__init__.py
Azure/az_invoke_parser.py
Jenkins/__init__.py
Jenkins/jenkins.py
RW/__init__.py
RW/CLI/CLI.py
RW/CLI/__init__.py
RW/CLI/cli_utils.py
RW/CLI/json_parser.py
RW/CLI/local_process.py
RW/CLI/postgres_helper.py
RW/CLI/stdout_parser.py
RW/K8sApplications/__init__.py
RW/K8sApplications/_test_parsers.py
RW/K8sApplications/k8s_applications.py
RW/K8sApplications/migrations_inspector.py
RW/K8sApplications/parsers.py
RW/K8sApplications/repository.py
RW/K8sHelper/__init__.py
RW/K8sHelper/k8s_helper.py
RW/K8sLog/__init__.py
RW/K8sLog/k8s_log.py
RW/NextSteps/Suggest.py
RW/NextSteps/__init__.py
rw_cli_keywords-0.0.25.dist-info/licenses/LICENSE
rw_cli_keywords-0.0.25.dist-info/METADATA
rw_cli_keywords-0.0.25.dist-info/WHEEL
rw_cli_keywords-0.0.25.dist-info/top_level.txt
rw_cli_keywords-0.0.25.dist-info/RECORD
