Metadata-Version: 2.4
Name: rw-cli-keywords
Version: 0.0.25
Summary: A set of RunWhen published CLI keywords and python libraries for interacting with APIs using CLIs
Author-email: RunWhen <info@runwhen.com>
License: Apache License 2.0
Project-URL: homepage, https://github.com/runwhen-contrib/rw-cli-codecollection
Classifier: Programming Language :: Python :: 3
Classifier: License :: OSI Approved :: Apache Software License
License-File: LICENSE
Requires-Dist: robotframework>=4.1.2
Requires-Dist: jmespath>=1.0.1
Requires-Dist: python-dateutil>=2.9.0
Requires-Dist: requests>=2.31.0
Requires-Dist: thefuzz>=0.20.0
Requires-Dist: pyyaml>=6.0.1
Requires-Dist: jinja2>=3.1.4
Requires-Dist: tabulate>=0.9.0
Requires-Dist: google-auth>=2.0.0
Dynamic: license-file
